{
  "name": "barbican-db-no-cp",
  "description": "Role for the Barbican Databases",
  "json_class": "Chef::Role",
  "default_attributes": {
  },
  "override_attributes": {
    "node_group": {
      "tag": "db",
      "description": "Barbican Database Node"
    }
  },
  "chef_type": "role",
  "run_list": [
    "recipe[authorized_keys]",
    "recipe[postgresql]",
    "recipe[postgresql::server]",
    "recipe[database::postgresql]",
    "recipe[database]",
    "recipe[barbican-db]"
  ],
  "env_run_lists": {
  }
}
